pyNutApi/__init__.py
pyNutApi/_lib.py
pyNutApi/nutApi.py
pynut_API-2.1.9.dist-info/LICENSE
pynut_API-2.1.9.dist-info/METADATA
pynut_API-2.1.9.dist-info/WHEEL
pynut_API-2.1.9.dist-info/top_level.txt
pynut_API-2.1.9.dist-info/RECORD
