Metadata-Version: 2.1
Name: pynut-API
Version: 2.1.9
Summary: Function easing life :)
Home-page: https://github.com/Laurent-Tupin/pynut_API
Author: Laurent Tupin
Author-email: laurent.tupinn@gmail.com
License: Copyright 2022-2035
Platform: UNKNOWN
Classifier: License :: Free For Home Use
Classifier: Programming Language :: Python :: 3
Classifier: Programming Language :: Python :: 3.9
License-File: LICENSE
Requires-Dist: pynut-tools (==2.2.5)
Requires-Dist: beautifulsoup4 (==4.7.1)
Requires-Dist: selenium (==3.141.0)
